lightrail_jupyterlab/__init__.py
lightrail_jupyterlab/_version.py
lightrail_jupyterlab-0.1.1.data/data/share/jupyter/labextensions/lightrail-jupyterlab/package.json
lightrail_jupyterlab-0.1.1.data/data/share/jupyter/labextensions/lightrail-jupyterlab/static/384.608b20c32fc88fdc48fa.js
lightrail_jupyterlab-0.1.1.data/data/share/jupyter/labextensions/lightrail-jupyterlab/static/568.67dcda9f9c1ef4d65729.js
lightrail_jupyterlab-0.1.1.data/data/share/jupyter/labextensions/lightrail-jupyterlab/static/747.e7328c5875094690e386.js
lightrail_jupyterlab-0.1.1.data/data/share/jupyter/labextensions/lightrail-jupyterlab/static/817.c1d8d57b1dfa7b8e78e9.js
lightrail_jupyterlab-0.1.1.data/data/share/jupyter/labextensions/lightrail-jupyterlab/static/remoteEntry.597b1654950155629956.js
lightrail_jupyterlab-0.1.1.data/data/share/jupyter/labextensions/lightrail-jupyterlab/static/style.js
lightrail_jupyterlab-0.1.1.data/data/share/jupyter/labextensions/lightrail-jupyterlab/static/third-party-licenses.json
lightrail_jupyterlab-0.1.1.data/data/share/jupyter/labextensions/lightrail-jupyterlab/install.json
lightrail_jupyterlab-0.1.1.dist-info/METADATA
lightrail_jupyterlab-0.1.1.dist-info/WHEEL
lightrail_jupyterlab-0.1.1.dist-info/licenses/LICENSE
lightrail_jupyterlab-0.1.1.dist-info/RECORD
