Metadata-Version: 2.1
Name: lightrail_jupyterlab
Version: 0.1.1
Summary: Connect JupyterLab to Lightrail AI
Project-URL: Homepage, https://github.com/lightrail-ai/lightrail
Project-URL: Bug Tracker, https://github.com/lightrail-ai/lightrail/issues
Project-URL: Repository, https://github.com/lightrail-ai/lightrail.git
Author-email: Lightrail <me@vishnumenon.com>
License: Copyright 2023 Vishnu Menon
License-File: LICENSE
Classifier: Framework :: Jupyter
Classifier: Framework :: Jupyter :: JupyterLab
Classifier: Framework :: Jupyter :: JupyterLab :: 4
Classifier: Framework :: Jupyter :: JupyterLab :: Extensions
Classifier: Framework :: Jupyter :: JupyterLab :: Extensions :: Prebuilt
Classifier: License :: OSI Approved :: BSD License
Classifier: Programming Language :: Python
Classifier: Programming Language :: Python :: 3
Classifier: Programming Language :: Python :: 3.8
Classifier: Programming Language :: Python :: 3.9
Classifier: Programming Language :: Python :: 3.10
Classifier: Programming Language :: Python :: 3.11
Requires-Python: >=3.8
